anpu/__init__.py
anpu-1.dist-info/LICENSE
anpu-1.dist-info/METADATA
anpu-1.dist-info/WHEEL
anpu-1.dist-info/top_level.txt
anpu-1.dist-info/RECORD
