Metadata-Version: 2.1
Name: anpu
Version: 1
Summary: A small library to search Spotify music.
Home-page: https://github.com/buyBread/anpu
Author: buyBread
Keywords: spotify,spotify api
Classifier: Intended Audience :: Developers
Classifier: Operating System :: Microsoft :: Windows
Classifier: Operating System :: MacOS :: MacOS X
Classifier: Operating System :: POSIX :: Linux
Classifier: Programming Language :: Python :: 3
License-File: LICENSE
Requires-Dist: requests
